[
  {
    "id": "trt1",
    "name": "TRT 1",
    "base_url": "https://www.trt1.com.tr",
    "active": true,
    "listings": [
      {
        "title": "Güncel Diziler",
        "path": "/diziler?archive=false&order=title_asc",
        "ishorizontal": true,
        "selectors": {
          "container": "div.grid_grid-wrapper__elAnh > div",
          "title": "div.card_card-title__IJ9af@text",
          "url": "a@href",
          "poster": "img@src"
        }
      },
      {
        "title": "Arşiv Diziler",
        "path": "/diziler?archive=true&order=title_asc",
        "ishorizontal": true,
        "selectors": {
          "container": "div.grid_grid-wrapper__elAnh > div",
          "title": "div.card_card-title__IJ9af@text",
          "url": "a@href",
          "poster": "img@src"
        }
      }
    ],
    "detail_page": {
      "selectors": {
        "title": "p.text_title__UMoMd@text",
        "description": "meta[name=description]@content",
        "poster": "img.card_card-image__T64bP@src",
        "tags": "",
        "year": "div.basic-dot_badge__1nsQT@text"
      }
    },
    "episode_page": {
      "path_suffix": "/bolum",
      "reverse_order": true,
      "selectors": {
        "container": "div.grid_grid-wrapper__elAnh > div.h-full.w-full > a",
        "name": "div.card_card-title__IJ9af@text",
        "url": "self@href"
      }
    },
    "video_extraction": {
      "methods": [
        {
          "type": "iframe",
          "selector": "iframe[src*='https']"
        },
        {
          "type": "youtube",
          "selector": "iframe[src*='youtube']"
        },
        {
          "type": "direct_m3u8"
        }
      ]
    }
  },
  {
    "id": "kanald",
    "name": "Kanal D",
    "base_url": "https://www.kanald.com.tr",
    "active": true,
    "headers": {
      "User-Agent": "Mozilla/5.0 (Windows NT 10.0; Win64; x64) AppleWebKit/537.36...",
      "Referer": "https://www.kanald.com.tr/"
    },
    "listings": [
      {
        "title": "Güncel Diziler",
        "path": "/diziler",
        "ishorizontal": false,
        "selectors": {
          "container": "div.item",
          "title": "img@alt",
          "url": "a@href",
          "poster": "img.lazy-common@data-src"
        }
      },
      {
        "title": "Arşiv",
        "path": "/diziler/arsiv",
        "ishorizontal": false,
        "selectors": {
          "container": "div.item",
          "title": "img@alt",
          "url": "a@href",
          "poster": "img.lazy-common@data-src"
        }
      }
    ],
    "detail_page": {
      "selectors": {
        "title": "img@alt",
        "description": "h1.listing-title",
        "poster": "img@src",
        "year": ".yil-deger@text",
        "tags": ".janr-etiket a@text"
      }
    },
    "episode_page": {
      "path_suffix": "/bolumler",
      "reverse_order": true,
      "selectors": {
        "container": "div.item",
        "name": "img@alt",
        "url": "a@href",
        "poster": "img.lazy-common@data-src"
      }
    },
    "video_extraction": {
      "methods": [
        {
          "type": "direct_m3u8",
          "selector": "contentUrl:@text"
        },
        {
          "type": "regex",
          "pattern": "contentUrl: \"(.*?)\""
        }
      ]
    }
  }
]
